tetpyclient/__init__.py
tetpyclient/tetpyclient.py
tetpyclient-1.0.7.dist-info/DESCRIPTION.rst
tetpyclient-1.0.7.dist-info/LICENSE.txt
tetpyclient-1.0.7.dist-info/METADATA
tetpyclient-1.0.7.dist-info/RECORD
tetpyclient-1.0.7.dist-info/WHEEL
tetpyclient-1.0.7.dist-info/metadata.json
tetpyclient-1.0.7.dist-info/top_level.txt
