Metadata-Version: 2.0
Name: tetpyclient
Version: 1.0.7
Summary: Python API Client for Tetration Analytics
Home-page: UNKNOWN
Author: Cisco Tetration Analytics
Author-email: openapi-dev@tetrationanalytics.com
License: Cisco API License
Platform: UNKNOWN
Requires-Dist: requests
Requires-Dist: requests-toolbelt
Requires-Dist: six
